[
    {
        "ref": {
            "lawNum": "令和三年内閣府令第三十五号",
            "lawArticle": {
                "provision": "MainProvision",
                "article": "4",
                "paragraph": "1",
                "item": "0"
            },
            "text": "令第十七条第一項第一号に規定する内閣府令で定めるものは、第四十八条第二号に掲げる預金等（同条第一号又は第三号に掲げるものに該当するものを除く。以下この項及び次節第五款において「外貨預金等」という。）のうち、その引出し、送金又は支払が当該外貨預金等の表示通貨で行うことができるものの受入れを内容とする契約とする。"
        },
        "referred": {
            "lawNum": "平成十二年政令第四百八十四号",
            "lawArticle": {
                "provision": "MainProvision",
                "article": "17",
                "paragraph": "1",
                "item": "1"
            },
            "text": "法第二十九条において読み替えて準用する銀行法第五十二条の四十四第二項に規定する特定預金等契約（国民の日常生活において利用される取引に係るものとして内閣府令で定めるものを除く。）"
        },
        "match": "内閣府令で定めるもの"
    },
    {
        "ref": {
            "lawNum": "令和三年内閣府令第三十五号",
            "lawArticle": {
                "provision": "MainProvision",
                "article": "4",
                "paragraph": "2",
                "item": "0"
            },
            "text": "令第十七条第二項第一号に規定する内閣府令で定めるものは、当座貸越しを内容とする契約とする。"
        },
        "referred": {
            "lawNum": "平成十二年政令第四百八十四号",
            "lawArticle": {
                "provision": "MainProvision",
                "article": "17",
                "paragraph": "2",
                "item": "1"
            },
            "text": "個人（事業として又は事業のために契約の当事者となる場合におけるものを除く。第二十条第一号において同じ。）である顧客との間の資金の貸付け又は手形の割引を内容とする契約のうち、当該顧客によりあらかじめ定められた条件に従った返済が行われることを条件として、当該顧客の請求に応じ、極度額の限度内において資金の貸付け又は手形の割引を行うことを約するもの（国民の日常生活において利用される取引に係るものとして内閣府令で定めるものを除く。）"
        },
        "match": "内閣府令で定めるもの"
    },
    {
        "ref": {
            "lawNum": "令和三年内閣府令第三十五号",
            "lawArticle": {
                "provision": "MainProvision",
                "article": "5",
                "paragraph": "1",
                "item": "0"
            },
            "text": "令第十八条第五号に規定する内閣府令で定めるものは、被保険者に対する行事の実施等に付随して引き受けられる保険に係る保険契約（当該行事の実施等に起因する損害等を対象とするものその他の当該行事の実施等と関連性を有するものに限る。）とする。"
        },
        "referred": {
            "lawNum": "平成十二年政令第四百八十四号",
            "lawArticle": {
                "provision": "MainProvision",
                "article": "18",
                "paragraph": "1",
                "item": "5"
            },
            "text": "団体保険（団体又はその代表者を保険契約者とし、当該団体に所属する者を被保険者とする保険をいう。）に係る保険契約（保険契約者等（法第十七条第一項に規定する保険契約者等をいう。第七号イにおいて同じ。）の保護に欠けるおそれがないものとして内閣府令で定めるものを除く。）"
        },
        "match": "内閣府令で定めるもの"
    },
    {
        "ref": {
            "lawNum": "令和三年内閣府令第三十五号",
            "lawArticle": {
                "provision": "MainProvision",
                "article": "5",
                "paragraph": "2",
                "item": "0"
            },
            "text": "令第十八条第六号に規定する内閣府令で定める保険契約は、次に掲げる保険契約とする。"
        },
        "referred": {
            "lawNum": "平成十二年政令第四百八十四号",
            "lawArticle": {
                "provision": "MainProvision",
                "article": "18",
                "paragraph": "1",
                "item": "6"
            },
            "text": "保険料の計算の基礎となる係数その他の事項について、顧客に対して必要な情報が適切に提供されることが特に必要なものとして内閣府令で定める保険契約"
        },
        "match": "内閣府令で定める保険契約"
    },
    {
        "ref": {
            "lawNum": "令和三年内閣府令第三十五号",
            "lawArticle": {
                "provision": "MainProvision",
                "article": "5",
                "paragraph": "3",
                "item": "0"
            },
            "text": "令第十八条第七号イに規定する内閣府令で定めるものは、第五十六条第一項第三号ロに掲げる保険契約とする。"
        },
        "referred": {
            "lawNum": "平成十二年政令第四百八十四号",
            "lawArticle": {
                "provision": "MainProvision",
                "article": "18",
                "paragraph": "1",
                "item": "7"
            },
            "text": "前各号に掲げる保険契約以外の保険契約で次のいずれかに該当するもの次の（１）から（３）までのいずれかに掲げる保険に係る保険契約（保険契約者等の保護に欠けるおそれがないものとして内閣府令で定めるものを除く。）であって、一の保険契約者に係る一の被保険者につきそれぞれ当該（１）から（３）までに定める金額を超える保険金の支払又は損害の塡補を約するもの保険業法第三条第四項第一号に掲げる保険千万円保険業法第三条第四項第二号又は第五項第二号に掲げる保険六百万円保険業法第三条第五項第一号に掲げる保険二千万円保険期間が被保険者の終身である保険に係る保険契約"
        },
        "match": "内閣府令で定めるもの"
    },
    {
        "ref": {
            "lawNum": "令和三年内閣府令第三十五号",
            "lawArticle": {
                "provision": "MainProvision",
                "article": "6",
                "paragraph": "1",
                "item": "0"
            },
            "text": "令第十九条第一項第一号イ（２）又はホ（２）に規定する内閣府令で定める要件は、次に掲げる要件の全てに該当することとする。"
        },
        "referred": {
            "lawNum": "平成十二年政令第四百八十四号",
            "lawArticle": {
                "provision": "MainProvision",
                "article": "19",
                "paragraph": "1",
                "item": "1"
            },
            "text": "有価証券（次に掲げる有価証券を除く。）の売買金融商品取引法第二条第一項第一号から第三号まで又は第五号に掲げる有価証券（新株予約権付社債券を除く。）のうち、次のいずれにも該当するものその取得勧誘（金融商品取引法第二条第三項に規定する取得勧誘をいう。以下この号において同じ。）が同項第一号に掲げる場合に該当するもの又はその売付け勧誘等（同条第四項に規定する売付け勧誘等をいう。以下この号において同じ。）が同条第四項第一号に掲げる場合に該当するもの償還の方法、期限その他の条件が内閣府令で定める要件に該当するもの金融商品取引法第二条第一項第六号、第七号又は第九号に掲げる有価証券（新株予約権証券を除く。）のうち、同条第十六項に規定する金融商品取引所若しくはこれに類似する取引所で外国に所在するもの（以下この号において「金融商品取引所等」という。）に上場されているもの（内閣府令で定めるものを除く。）又は金融商品取引所等が売買のため上場することを承認したもの金融商品取引法第二条第一項第十号に掲げる有価証券のうち、次のいずれにも該当するもの次のいずれかに該当するものその取得勧誘が金融商品取引法第二条第三項第一号に掲げる場合に該当するもの又はその売付け勧誘等が同条第四項第一号に掲げる場合に該当するもの金融商品取引所等に上場されているもの（内閣府令で定めるものを除く。）又は金融商品取引所等が売買のため上場することを承認したもの有価証券（イからリまで（イ（１）、ハ（１）、ニ（１）及びホ（１）に係る部分を除く。）に掲げる有価証券を除く。ニ（２）及びヘ（２）において同じ。）又はデリバティブ取引（金融商品取引法第二条第二十項に規定するデリバティブ取引をいう。以下この項において同じ。）（これに類するものとして内閣府令で定める取引を含む。ニ（２）及びヘ（２）において同じ。）に係る権利を信託財産とするもの（内閣府令で定める目的により信託財産とするものを除く。）でないもの金融商品取引法第二条第一項第十一号に掲げる有価証券（投資証券（投資信託及び投資法人に関する法律（昭和二十六年法律第百九十八号）第二条第十五項に規定する投資証券をいう。ニにおいて同じ。）又は外国投資証券（投資信託及び投資法人に関する法律第二百二十条第一項に規定する外国投資証券をいう。ホにおいて同じ。）で投資証券に類する証券に限る。）のうち、次のいずれにも該当するもの次のいずれかに該当するものその取得勧誘が金融商品取引法第二条第三項第一号に掲げる場合に該当するもの又はその売付け勧誘等が同条第四項第一号に掲げる場合に該当するもの金融商品取引所等に上場されているもの（内閣府令で定めるものを除く。）又は金融商品取引所等が売買のため上場することを承認したもの有価証券又はデリバティブ取引に係る権利を投資の対象とする資産とするもの（内閣府令で定める目的により投資の対象とする資産とするものを除く。）でないもの金融商品取引法第二条第一項第十一号に掲げる有価証券（投資法人債券（投資信託及び投資法人に関する法律第二条第二十項に規定する投資法人債券をいう。ホにおいて同じ。）又は外国投資証券で投資法人債券に類する証券に限る。）のうち、次のいずれにも該当するものその取得勧誘が金融商品取引法第二条第三項第一号に掲げる場合に該当するもの又はその売付け勧誘等が同条第四項第一号に掲げる場合に該当するもの償還の方法、期限その他の条件が内閣府令で定める要件に該当するもの金融商品取引法第二条第一項第十四号に掲げる有価証券のうち、次のいずれにも該当するもの金融商品取引所等に上場されているもの（内閣府令で定めるものを除く。）又は金融商品取引所等が売買のため上場することを承認したもの主として特定資産（投資信託及び投資法人に関する法律第二条第一項に規定する特定資産をいう。）を信託財産とするもののうち、有価証券又はデリバティブ取引に係る権利を信託財産とするもの（内閣府令で定める目的により信託財産とするものを除く。）でないもの金融商品取引法第二条第一項第十七号に掲げる有価証券のうちイ、ロ又はヘに掲げる有価証券の性質を有するもの金融商品取引法第二条第一項第二十号に掲げる有価証券でイからトまでに掲げる有価証券に係る権利を表示するもののうち、金融商品取引所等に上場されているもの（内閣府令で定めるものを除く。）又は金融商品取引所等が売買のため上場することを承認したものイからチまでに掲げる有価証券に表示されるべき権利であって、金融商品取引法第二条第二項の規定により有価証券とみなされるもの"
        },
        "match": "内閣府令で定める要件"
    },
    {
        "ref": {
            "lawNum": "令和三年内閣府令第三十五号",
            "lawArticle": {
                "provision": "MainProvision",
                "article": "6",
                "paragraph": "2",
                "item": "0"
            },
            "text": "令第十九条第一項第一号ロ、ハ（１）（ｉｉ）、ニ（１）（ｉｉ）、ヘ（１）又はチに規定する内閣府令で定めるものは、有価証券が上場されている同号ロに規定する金融商品取引所等の定める規則に基づき、当該金融商品取引所等への上場を廃止することが決定された銘柄又は上場を廃止するおそれがある銘柄として指定されている有価証券とする。"
        },
        "referred": {
            "lawNum": "平成十二年政令第四百八十四号",
            "lawArticle": {
                "provision": "MainProvision",
                "article": "19",
                "paragraph": "1",
                "item": "1"
            },
            "text": "有価証券（次に掲げる有価証券を除く。）の売買金融商品取引法第二条第一項第一号から第三号まで又は第五号に掲げる有価証券（新株予約権付社債券を除く。）のうち、次のいずれにも該当するものその取得勧誘（金融商品取引法第二条第三項に規定する取得勧誘をいう。以下この号において同じ。）が同項第一号に掲げる場合に該当するもの又はその売付け勧誘等（同条第四項に規定する売付け勧誘等をいう。以下この号において同じ。）が同条第四項第一号に掲げる場合に該当するもの償還の方法、期限その他の条件が内閣府令で定める要件に該当するもの金融商品取引法第二条第一項第六号、第七号又は第九号に掲げる有価証券（新株予約権証券を除く。）のうち、同条第十六項に規定する金融商品取引所若しくはこれに類似する取引所で外国に所在するもの（以下この号において「金融商品取引所等」という。）に上場されているもの（内閣府令で定めるものを除く。）又は金融商品取引所等が売買のため上場することを承認したもの金融商品取引法第二条第一項第十号に掲げる有価証券のうち、次のいずれにも該当するもの次のいずれかに該当するものその取得勧誘が金融商品取引法第二条第三項第一号に掲げる場合に該当するもの又はその売付け勧誘等が同条第四項第一号に掲げる場合に該当するもの金融商品取引所等に上場されているもの（内閣府令で定めるものを除く。）又は金融商品取引所等が売買のため上場することを承認したもの有価証券（イからリまで（イ（１）、ハ（１）、ニ（１）及びホ（１）に係る部分を除く。）に掲げる有価証券を除く。ニ（２）及びヘ（２）において同じ。）又はデリバティブ取引（金融商品取引法第二条第二十項に規定するデリバティブ取引をいう。以下この項において同じ。）（これに類するものとして内閣府令で定める取引を含む。ニ（２）及びヘ（２）において同じ。）に係る権利を信託財産とするもの（内閣府令で定める目的により信託財産とするものを除く。）でないもの金融商品取引法第二条第一項第十一号に掲げる有価証券（投資証券（投資信託及び投資法人に関する法律（昭和二十六年法律第百九十八号）第二条第十五項に規定する投資証券をいう。ニにおいて同じ。）又は外国投資証券（投資信託及び投資法人に関する法律第二百二十条第一項に規定する外国投資証券をいう。ホにおいて同じ。）で投資証券に類する証券に限る。）のうち、次のいずれにも該当するもの次のいずれかに該当するものその取得勧誘が金融商品取引法第二条第三項第一号に掲げる場合に該当するもの又はその売付け勧誘等が同条第四項第一号に掲げる場合に該当するもの金融商品取引所等に上場されているもの（内閣府令で定めるものを除く。）又は金融商品取引所等が売買のため上場することを承認したもの有価証券又はデリバティブ取引に係る権利を投資の対象とする資産とするもの（内閣府令で定める目的により投資の対象とする資産とするものを除く。）でないもの金融商品取引法第二条第一項第十一号に掲げる有価証券（投資法人債券（投資信託及び投資法人に関する法律第二条第二十項に規定する投資法人債券をいう。ホにおいて同じ。）又は外国投資証券で投資法人債券に類する証券に限る。）のうち、次のいずれにも該当するものその取得勧誘が金融商品取引法第二条第三項第一号に掲げる場合に該当するもの又はその売付け勧誘等が同条第四項第一号に掲げる場合に該当するもの償還の方法、期限その他の条件が内閣府令で定める要件に該当するもの金融商品取引法第二条第一項第十四号に掲げる有価証券のうち、次のいずれにも該当するもの金融商品取引所等に上場されているもの（内閣府令で定めるものを除く。）又は金融商品取引所等が売買のため上場することを承認したもの主として特定資産（投資信託及び投資法人に関する法律第二条第一項に規定する特定資産をいう。）を信託財産とするもののうち、有価証券又はデリバティブ取引に係る権利を信託財産とするもの（内閣府令で定める目的により信託財産とするものを除く。）でないもの金融商品取引法第二条第一項第十七号に掲げる有価証券のうちイ、ロ又はヘに掲げる有価証券の性質を有するもの金融商品取引法第二条第一項第二十号に掲げる有価証券でイからトまでに掲げる有価証券に係る権利を表示するもののうち、金融商品取引所等に上場されているもの（内閣府令で定めるものを除く。）又は金融商品取引所等が売買のため上場することを承認したものイからチまでに掲げる有価証券に表示されるべき権利であって、金融商品取引法第二条第二項の規定により有価証券とみなされるもの"
        },
        "match": "内閣府令で定めるもの"
    },
    {
        "ref": {
            "lawNum": "令和三年内閣府令第三十五号",
            "lawArticle": {
                "provision": "MainProvision",
                "article": "6",
                "paragraph": "3",
                "item": "0"
            },
            "text": "令第十九条第一項第一号ハ（２）に規定する内閣府令で定める取引は、次に掲げる取引とする。"
        },
        "referred": {
            "lawNum": "平成十二年政令第四百八十四号",
            "lawArticle": {
                "provision": "MainProvision",
                "article": "19",
                "paragraph": "1",
                "item": "1"
            },
            "text": "有価証券（次に掲げる有価証券を除く。）の売買金融商品取引法第二条第一項第一号から第三号まで又は第五号に掲げる有価証券（新株予約権付社債券を除く。）のうち、次のいずれにも該当するものその取得勧誘（金融商品取引法第二条第三項に規定する取得勧誘をいう。以下この号において同じ。）が同項第一号に掲げる場合に該当するもの又はその売付け勧誘等（同条第四項に規定する売付け勧誘等をいう。以下この号において同じ。）が同条第四項第一号に掲げる場合に該当するもの償還の方法、期限その他の条件が内閣府令で定める要件に該当するもの金融商品取引法第二条第一項第六号、第七号又は第九号に掲げる有価証券（新株予約権証券を除く。）のうち、同条第十六項に規定する金融商品取引所若しくはこれに類似する取引所で外国に所在するもの（以下この号において「金融商品取引所等」という。）に上場されているもの（内閣府令で定めるものを除く。）又は金融商品取引所等が売買のため上場することを承認したもの金融商品取引法第二条第一項第十号に掲げる有価証券のうち、次のいずれにも該当するもの次のいずれかに該当するものその取得勧誘が金融商品取引法第二条第三項第一号に掲げる場合に該当するもの又はその売付け勧誘等が同条第四項第一号に掲げる場合に該当するもの金融商品取引所等に上場されているもの（内閣府令で定めるものを除く。）又は金融商品取引所等が売買のため上場することを承認したもの有価証券（イからリまで（イ（１）、ハ（１）、ニ（１）及びホ（１）に係る部分を除く。）に掲げる有価証券を除く。ニ（２）及びヘ（２）において同じ。）又はデリバティブ取引（金融商品取引法第二条第二十項に規定するデリバティブ取引をいう。以下この項において同じ。）（これに類するものとして内閣府令で定める取引を含む。ニ（２）及びヘ（２）において同じ。）に係る権利を信託財産とするもの（内閣府令で定める目的により信託財産とするものを除く。）でないもの金融商品取引法第二条第一項第十一号に掲げる有価証券（投資証券（投資信託及び投資法人に関する法律（昭和二十六年法律第百九十八号）第二条第十五項に規定する投資証券をいう。ニにおいて同じ。）又は外国投資証券（投資信託及び投資法人に関する法律第二百二十条第一項に規定する外国投資証券をいう。ホにおいて同じ。）で投資証券に類する証券に限る。）のうち、次のいずれにも該当するもの次のいずれかに該当するものその取得勧誘が金融商品取引法第二条第三項第一号に掲げる場合に該当するもの又はその売付け勧誘等が同条第四項第一号に掲げる場合に該当するもの金融商品取引所等に上場されているもの（内閣府令で定めるものを除く。）又は金融商品取引所等が売買のため上場することを承認したもの有価証券又はデリバティブ取引に係る権利を投資の対象とする資産とするもの（内閣府令で定める目的により投資の対象とする資産とするものを除く。）でないもの金融商品取引法第二条第一項第十一号に掲げる有価証券（投資法人債券（投資信託及び投資法人に関する法律第二条第二十項に規定する投資法人債券をいう。ホにおいて同じ。）又は外国投資証券で投資法人債券に類する証券に限る。）のうち、次のいずれにも該当するものその取得勧誘が金融商品取引法第二条第三項第一号に掲げる場合に該当するもの又はその売付け勧誘等が同条第四項第一号に掲げる場合に該当するもの償還の方法、期限その他の条件が内閣府令で定める要件に該当するもの金融商品取引法第二条第一項第十四号に掲げる有価証券のうち、次のいずれにも該当するもの金融商品取引所等に上場されているもの（内閣府令で定めるものを除く。）又は金融商品取引所等が売買のため上場することを承認したもの主として特定資産（投資信託及び投資法人に関する法律第二条第一項に規定する特定資産をいう。）を信託財産とするもののうち、有価証券又はデリバティブ取引に係る権利を信託財産とするもの（内閣府令で定める目的により信託財産とするものを除く。）でないもの金融商品取引法第二条第一項第十七号に掲げる有価証券のうちイ、ロ又はヘに掲げる有価証券の性質を有するもの金融商品取引法第二条第一項第二十号に掲げる有価証券でイからトまでに掲げる有価証券に係る権利を表示するもののうち、金融商品取引所等に上場されているもの（内閣府令で定めるものを除く。）又は金融商品取引所等が売買のため上場することを承認したものイからチまでに掲げる有価証券に表示されるべき権利であって、金融商品取引法第二条第二項の規定により有価証券とみなされるもの"
        },
        "match": "内閣府令で定める取引"
    },
    {
        "ref": {
            "lawNum": "令和三年内閣府令第三十五号",
            "lawArticle": {
                "provision": "MainProvision",
                "article": "6",
                "paragraph": "4",
                "item": "0"
            },
            "text": "令第十九条第一項第一号ハ（２）、ニ（２）又はヘ（２）に規定する内閣府令で定める目的は、次に掲げる目的とする。"
        },
        "referred": {
            "lawNum": "平成十二年政令第四百八十四号",
            "lawArticle": {
                "provision": "MainProvision",
                "article": "19",
                "paragraph": "1",
                "item": "1"
            },
            "text": "有価証券（次に掲げる有価証券を除く。）の売買金融商品取引法第二条第一項第一号から第三号まで又は第五号に掲げる有価証券（新株予約権付社債券を除く。）のうち、次のいずれにも該当するものその取得勧誘（金融商品取引法第二条第三項に規定する取得勧誘をいう。以下この号において同じ。）が同項第一号に掲げる場合に該当するもの又はその売付け勧誘等（同条第四項に規定する売付け勧誘等をいう。以下この号において同じ。）が同条第四項第一号に掲げる場合に該当するもの償還の方法、期限その他の条件が内閣府令で定める要件に該当するもの金融商品取引法第二条第一項第六号、第七号又は第九号に掲げる有価証券（新株予約権証券を除く。）のうち、同条第十六項に規定する金融商品取引所若しくはこれに類似する取引所で外国に所在するもの（以下この号において「金融商品取引所等」という。）に上場されているもの（内閣府令で定めるものを除く。）又は金融商品取引所等が売買のため上場することを承認したもの金融商品取引法第二条第一項第十号に掲げる有価証券のうち、次のいずれにも該当するもの次のいずれかに該当するものその取得勧誘が金融商品取引法第二条第三項第一号に掲げる場合に該当するもの又はその売付け勧誘等が同条第四項第一号に掲げる場合に該当するもの金融商品取引所等に上場されているもの（内閣府令で定めるものを除く。）又は金融商品取引所等が売買のため上場することを承認したもの有価証券（イからリまで（イ（１）、ハ（１）、ニ（１）及びホ（１）に係る部分を除く。）に掲げる有価証券を除く。ニ（２）及びヘ（２）において同じ。）又はデリバティブ取引（金融商品取引法第二条第二十項に規定するデリバティブ取引をいう。以下この項において同じ。）（これに類するものとして内閣府令で定める取引を含む。ニ（２）及びヘ（２）において同じ。）に係る権利を信託財産とするもの（内閣府令で定める目的により信託財産とするものを除く。）でないもの金融商品取引法第二条第一項第十一号に掲げる有価証券（投資証券（投資信託及び投資法人に関する法律（昭和二十六年法律第百九十八号）第二条第十五項に規定する投資証券をいう。ニにおいて同じ。）又は外国投資証券（投資信託及び投資法人に関する法律第二百二十条第一項に規定する外国投資証券をいう。ホにおいて同じ。）で投資証券に類する証券に限る。）のうち、次のいずれにも該当するもの次のいずれかに該当するものその取得勧誘が金融商品取引法第二条第三項第一号に掲げる場合に該当するもの又はその売付け勧誘等が同条第四項第一号に掲げる場合に該当するもの金融商品取引所等に上場されているもの（内閣府令で定めるものを除く。）又は金融商品取引所等が売買のため上場することを承認したもの有価証券又はデリバティブ取引に係る権利を投資の対象とする資産とするもの（内閣府令で定める目的により投資の対象とする資産とするものを除く。）でないもの金融商品取引法第二条第一項第十一号に掲げる有価証券（投資法人債券（投資信託及び投資法人に関する法律第二条第二十項に規定する投資法人債券をいう。ホにおいて同じ。）又は外国投資証券で投資法人債券に類する証券に限る。）のうち、次のいずれにも該当するものその取得勧誘が金融商品取引法第二条第三項第一号に掲げる場合に該当するもの又はその売付け勧誘等が同条第四項第一号に掲げる場合に該当するもの償還の方法、期限その他の条件が内閣府令で定める要件に該当するもの金融商品取引法第二条第一項第十四号に掲げる有価証券のうち、次のいずれにも該当するもの金融商品取引所等に上場されているもの（内閣府令で定めるものを除く。）又は金融商品取引所等が売買のため上場することを承認したもの主として特定資産（投資信託及び投資法人に関する法律第二条第一項に規定する特定資産をいう。）を信託財産とするもののうち、有価証券又はデリバティブ取引に係る権利を信託財産とするもの（内閣府令で定める目的により信託財産とするものを除く。）でないもの金融商品取引法第二条第一項第十七号に掲げる有価証券のうちイ、ロ又はヘに掲げる有価証券の性質を有するもの金融商品取引法第二条第一項第二十号に掲げる有価証券でイからトまでに掲げる有価証券に係る権利を表示するもののうち、金融商品取引所等に上場されているもの（内閣府令で定めるものを除く。）又は金融商品取引所等が売買のため上場することを承認したものイからチまでに掲げる有価証券に表示されるべき権利であって、金融商品取引法第二条第二項の規定により有価証券とみなされるもの"
        },
        "match": "内閣府令で定める目的"
    },
    {
        "ref": {
            "lawNum": "令和三年内閣府令第三十五号",
            "lawArticle": {
                "provision": "MainProvision",
                "article": "6",
                "paragraph": "5",
                "item": "0"
            },
            "text": "令第十九条第一項第二号に規定する内閣府令で定める取引は、次に掲げる取引とする。"
        },
        "referred": {
            "lawNum": "平成十二年政令第四百八十四号",
            "lawArticle": {
                "provision": "MainProvision",
                "article": "19",
                "paragraph": "1",
                "item": "2"
            },
            "text": "前号イからリまでに掲げる有価証券の売買のうち、デリバティブ取引、信用取引（法第三十一条第二項において読み替えて準用する金融商品取引法第三十七条の三第一項第一号に規定する相手方金融機関であって、金融商品取引業者（同法第二条第九項に規定する金融商品取引業者をいう。第三十条第一項において同じ。）である者が顧客に信用を供与して行うものをいう。）その他内閣府令で定める取引に該当するもの"
        },
        "match": "内閣府令で定める取引"
    },
    {
        "ref": {
            "lawNum": "令和三年内閣府令第三十五号",
            "lawArticle": {
                "provision": "MainProvision",
                "article": "17",
                "paragraph": "1",
                "item": "0"
            },
            "text": "令第二十三条に規定する内閣府令で定めるものは、次に掲げる者とする。"
        },
        "referred": {
            "lawNum": "平成十二年政令第四百八十四号",
            "lawArticle": {
                "provision": "MainProvision",
                "article": "23",
                "paragraph": "1",
                "item": "0"
            },
            "text": "法第十五条第七号（法第十六条第二項において読み替えて準用する場合を含む。）に規定する政令で定める使用人は、貸金業貸付媒介業務に関し営業所又は事務所の業務を統括する者その他これに準ずる者で内閣府令で定めるものとする。"
        },
        "match": "内閣府令で定めるもの"
    },
    {
        "ref": {
            "lawNum": "令和三年内閣府令第三十五号",
            "lawArticle": {
                "provision": "MainProvision",
                "article": "29",
                "paragraph": "1",
                "item": "0"
            },
            "text": "令第二十七条に規定する内閣府令で定める金融機関は、次に掲げる金融機関とする。"
        },
        "referred": {
            "lawNum": "平成十二年政令第四百八十四号",
            "lawArticle": {
                "provision": "MainProvision",
                "article": "27",
                "paragraph": "1",
                "item": "0"
            },
            "text": "金融サービス仲介業者は、法第二十二条第三項の契約を締結する場合には、銀行（銀行法第二条第一項に規定する銀行をいう。第三十条第一項において同じ。）、保険会社（保険業法第二百十九条第一項の免許を受けた同項に規定する特定法人の同項に規定する引受社員を含む。）その他内閣府令で定める金融機関を相手方とし、その内容を次に掲げる要件に適合するものとしなければならない。"
        },
        "match": "内閣府令で定める金融機関"
    },
    {
        "ref": {
            "lawNum": "令和三年内閣府令第三十五号",
            "lawArticle": {
                "provision": "MainProvision",
                "article": "41",
                "paragraph": "1",
                "item": "0"
            },
            "text": "令第三十条第一項各号列記以外の部分に規定する内閣府令で定める者は、次に掲げる者とする。"
        },
        "referred": {
            "lawNum": "平成十二年政令第四百八十四号",
            "lawArticle": {
                "provision": "MainProvision",
                "article": "30",
                "paragraph": "1",
                "item": "0"
            },
            "text": "法第二十七条に規定する政令で定める者は、銀行、金融商品取引業者（有価証券等管理業務（金融商品取引法第二十八条第五項に規定する有価証券等管理業務をいう。）を行う者に限る。）その他内閣府令で定める者以外の者であって、次に掲げるものとする。"
        },
        "match": "内閣府令で定める者"
    },
    {
        "ref": {
            "lawNum": "令和三年内閣府令第三十五号",
            "lawArticle": {
                "provision": "MainProvision",
                "article": "42",
                "paragraph": "1",
                "item": "0"
            },
            "text": "令第三十条第二項及び第三項に規定する内閣府令で定める者は、次に掲げる者とする。"
        },
        "referred": {
            "lawNum": "平成十二年政令第四百八十四号",
            "lawArticle": {
                "provision": "MainProvision",
                "article": "30",
                "paragraph": "2",
                "item": "0"
            },
            "text": "前項第三号の「親法人等」とは、次に掲げる者（内閣府令で定める者を除く。）をいう。"
        },
        "match": "内閣府令で定める者"
    },
    {
        "ref": {
            "lawNum": "令和三年内閣府令第三十五号",
            "lawArticle": {
                "provision": "MainProvision",
                "article": "43",
                "paragraph": "1",
                "item": "0"
            },
            "text": "令第三十条第四項に規定する内閣府令で定めるものは、次に掲げる会社等（同項に規定する会社等をいう。以下この条から第四十五条までにおいて同じ。）とする。"
        },
        "referred": {
            "lawNum": "平成十二年政令第四百八十四号",
            "lawArticle": {
                "provision": "MainProvision",
                "article": "30",
                "paragraph": "4",
                "item": "0"
            },
            "text": "この条において「親会社等」とは、他の会社等（会社、組合その他これらに準ずる事業体（外国におけるこれらに相当するものを含む。）をいう。以下この項及び次項において同じ。）の財務及び営業又は事業の方針を決定する機関（株主総会その他これに準ずる機関をいう。以下この項において「意思決定機関」という。）を支配している会社等として内閣府令で定めるものをいい、「子会社等」とは、親会社等によりその意思決定機関を支配されている他の会社等をいう。この場合において、親会社等及び子会社等又は子会社等が他の会社等の意思決定機関を支配している場合における当該他の会社等は、その親会社等の子会社等とみなす。"
        },
        "match": "内閣府令で定めるもの"
    },
    {
        "ref": {
            "lawNum": "令和三年内閣府令第三十五号",
            "lawArticle": {
                "provision": "MainProvision",
                "article": "44",
                "paragraph": "1",
                "item": "0"
            },
            "text": "令第三十条第五項に規定する内閣府令で定めるものは、次に掲げる会社等とする。"
        },
        "referred": {
            "lawNum": "平成十二年政令第四百八十四号",
            "lawArticle": {
                "provision": "MainProvision",
                "article": "30",
                "paragraph": "5",
                "item": "0"
            },
            "text": "第二項第三号及び第四号イ並びに第三項第二号の「関連会社等」とは、会社等（当該会社等の子会社等を含む。）が出資、取締役その他これに準ずる役職への当該会社等の役員（法第十三条第一項第二号に規定する役員をいう。第三十九条第一項第三号において同じ。）若しくは使用人である者若しくはこれらであった者の就任、融資、債務の保証若しくは担保の提供、技術の提供又は営業上若しくは事業上の取引等を通じて、財務及び営業又は事業の方針の決定に対して重要な影響を与えることができる他の会社等（子会社等を除く。）として内閣府令で定めるものをいう。"
        },
        "match": "内閣府令で定めるもの"
    },
    {
        "ref": {
            "lawNum": "令和三年内閣府令第三十五号",
            "lawArticle": {
                "provision": "MainProvision",
                "article": "84",
                "paragraph": "1",
                "item": "0"
            },
            "text": "令第三十五条第一項第一号に規定する内閣府令で定めるものは、手数料等の種類ごとの金額若しくはその上限額又はこれらの計算方法（特定預金等契約にあっては当該特定預金等契約に係る元本の額に対する割合を含み、特定金融サービス契約（特定預金等契約及び特定保険契約を除く。）にあっては当該特定金融サービス契約に係る有価証券の価格若しくは運用財産（金融商品取引法第三十五条第一項第十五号に規定する運用財産をいう。第九十二条第一項及び第百十一条第一項第十九号において同じ。）の額に対する割合又は当該特定金融サービス契約を締結することにより生じた利益に対する割合を含む。以下この項において同じ。）の概要及び当該金額の合計額若しくはその上限額又はこれらの計算方法の概要とする。"
        },
        "referred": {
            "lawNum": "平成十二年政令第四百八十四号",
            "lawArticle": {
                "provision": "MainProvision",
                "article": "35",
                "paragraph": "1",
                "item": "1"
            },
            "text": "特定金融サービス契約（法第三十一条第二項に規定する特定金融サービス契約をいう。次号及び次項第一号において同じ。）に関して顧客が支払うべき手数料、報酬その他の対価に関する事項であって内閣府令で定めるもの"
        },
        "match": "内閣府令で定めるもの"
    },
    {
        "ref": {
            "lawNum": "令和三年内閣府令第三十五号",
            "lawArticle": {
                "provision": "MainProvision",
                "article": "85",
                "paragraph": "1",
                "item": "0"
            },
            "text": "令第三十五条第一項第三号に規定する内閣府令で定める事項は、次に掲げる事項とする。"
        },
        "referred": {
            "lawNum": "平成十二年政令第四百八十四号",
            "lawArticle": {
                "provision": "MainProvision",
                "article": "35",
                "paragraph": "1",
                "item": "3"
            },
            "text": "前二号に掲げる事項に準ずるものとして内閣府令で定める事項"
        },
        "match": "内閣府令で定める事項"
    },
    {
        "ref": {
            "lawNum": "令和三年内閣府令第三十五号",
            "lawArticle": {
                "provision": "MainProvision",
                "article": "86",
                "paragraph": "1",
                "item": "0"
            },
            "text": "令第三十五条第二項に規定する内閣府令で定める方法は、次に掲げる方法とする。"
        },
        "referred": {
            "lawNum": "平成十二年政令第四百八十四号",
            "lawArticle": {
                "provision": "MainProvision",
                "article": "35",
                "paragraph": "2",
                "item": "0"
            },
            "text": "準用金融商品取引法第三十七条第一項に規定する行為を基幹放送事業者（放送法（昭和二十五年法律第百三十二号）第二条第二十三号に規定する基幹放送事業者をいい、日本放送協会及び放送大学学園（放送大学学園法（平成十四年法律第百五十六号）第三条に規定する放送大学学園をいう。）を除く。）の放送設備により放送をさせる方法その他これに準ずるものとして内閣府令で定める方法によりする場合における同項第三号に規定する政令で定めるものは、前項の規定にかかわらず、次に掲げる事項とする。"
        },
        "match": "内閣府令で定める方法"
    },
    {
        "ref": {
            "lawNum": "令和三年内閣府令第三十五号",
            "lawArticle": {
                "provision": "MainProvision",
                "article": "86",
                "paragraph": "2",
                "item": "0"
            },
            "text": "令第三十五条第二項第二号に規定する内閣府令で定める事項は、第八十二条第三号イ（４）又はロ（４）に掲げる事項とする。"
        },
        "referred": {
            "lawNum": "平成十二年政令第四百八十四号",
            "lawArticle": {
                "provision": "MainProvision",
                "article": "35",
                "paragraph": "2",
                "item": "2"
            },
            "text": "前号に掲げる事項に準ずるものとして内閣府令で定める事項"
        },
        "match": "内閣府令で定める事項"
    },
    {
        "ref": {
            "lawNum": "令和三年内閣府令第三十五号",
            "lawArticle": {
                "provision": "MainProvision",
                "article": "142",
                "paragraph": "1",
                "item": "0"
            },
            "text": "令第三十九条第二項に規定する内閣府令で定める書類は、次に掲げる書類とする。"
        },
        "referred": {
            "lawNum": "平成十二年政令第四百八十四号",
            "lawArticle": {
                "provision": "MainProvision",
                "article": "39",
                "paragraph": "2",
                "item": "0"
            },
            "text": "前項の申請書には、定款、登記事項証明書その他内閣府令で定める書類を添付しなければならない。"
        },
        "match": "内閣府令で定める書類"
    },
    {
        "ref": {
            "lawNum": "令和三年内閣府令第三十五号",
            "lawArticle": {
                "provision": "MainProvision",
                "article": "169",
                "paragraph": "1",
                "item": "0"
            },
            "text": "令第四十三条第一項に規定する内閣府令で定める額は、千円とする。"
        },
        "referred": {
            "lawNum": "平成十二年政令第四百八十四号",
            "lawArticle": {
                "provision": "MainProvision",
                "article": "43",
                "paragraph": "1",
                "item": "0"
            },
            "text": "法第七十九条第一項の規定による登録手数料の額は、外務員（法第七十五条第一項に規定する外務員をいう。第四十七条第四項及び第四十八条第四項において同じ。）一人につき三千円を超えない範囲内において実費を勘案して内閣府令で定める額とする。"
        },
        "match": "内閣府令で定める額"
    },
    {
        "ref": {
            "lawNum": "平成七年政令第四百二十五号",
            "lawArticle": {
                "provision": "MainProvision",
                "article": "37_4_5",
                "paragraph": "1",
                "item": "0"
            },
            "text": "法第二百七十条の六第三項に規定する政令で定める法令は、臨時金利調整法（昭和二十二年法律第百八十一号）、消防法（昭和二十三年法律第百八十六号）、損害保険料率算出団体に関する法律（昭和二十三年法律第百九十三号）、相続税法（昭和二十五年法律第七十三号）、船主相互保険組合法（昭和二十五年法律第百七十七号）、地方税法（昭和二十五年法律第二百二十六号）、税理士法（昭和二十六年法律第二百三十七号）、漁船損害等補償法（昭和二十七年法律第二十八号）、出資の受入れ、預り金及び金利等の取締りに関する法律（昭和二十九年法律第百九十五号）、住宅融資保険法（昭和三十年法律第六十三号）、自動車損害賠償保障法（昭和三十年法律第九十七号）、準備預金制度に関する法律（昭和三十二年法律第百三十五号）、国民年金法（昭和三十四年法律第百四十一号）、原子力損害の賠償に関する法律、所得税法（昭和四十年法律第三十三号）、地震保険に関する法律（昭和四十一年法律第七十三号）、印紙税法（昭和四十二年法律第二十三号）、勤労者財産形成促進法（昭和四十六年法律第九十二号）、船舶油濁等損害賠償保障法（昭和五十年法律第九十五号）、確定給付企業年金法（平成十三年法律第五十号）、犯罪による収益の移転防止に関する法律、人工衛星等の打上げ及び人工衛星の管理に関する法律、予算決算及び会計令（昭和二十二年勅令第百六十五号）、相続税法施行令（昭和二十五年政令第七十一号）、中小企業信用保険法施行令（昭和二十五年政令第三百五十号）、漁船損害等補償法施行令（昭和二十七年政令第六十八号）、公認会計士法施行令（昭和二十七年政令第三百四十三号）、貿易保険法施行令、関税法施行令（昭和二十九年政令第百五十号）、自動車損害賠償保障法施行令（昭和三十年政令第二百八十六号）、自動車事故対策事業賦課金等の金額を定める政令（昭和三十年政令第三百十六号）、割賦販売法施行令（昭和三十六年政令第三百四十一号）、所得税法施行令（昭和四十年政令第九十六号）、法人税法施行令（昭和四十年政令第九十七号）、金融商品取引法施行令、地震保険に関する法律施行令（昭和四十一年政令第百六十四号）、印紙税法施行令（昭和四十二年政令第百八号）、外航船舶建造融資利子補給臨時措置法施行令（昭和四十四年政令第百九十五号）、船舶油濁等損害賠償保障法施行令、船舶の所有者等の責任の制限に関する法律施行令、国家公務員共済組合及び国家公務員共済組合連合会が行う国家公務員等の財産形成事業に関する政令（昭和五十二年政令第百九十九号）、地方公務員共済組合等が行う地方公務員等の財産形成事業に関する政令（昭和五十三年政令第二十五号）、ゴルフ場等に係る会員契約の適正化に関する法律施行令、金融機関の信託業務の兼営等に関する法律施行令、金融サービスの提供及び利用環境の整備等に関する法律施行令（平成十二年政令第四百八十四号）、信託業法施行令、資金決済に関する法律施行令（平成二十二年政令第十九号）及び株式会社国際協力銀行法施行令（平成二十三年政令第二百二十一号）とし、臨時金利調整法第一条第一項、消防法第三十三条、相続税法第五十九条第一項第一号及び第二項、税理士法第五条第一項第一号ハ、漁船損害等補償法第百十二条第七項、出資の受入れ、預り金及び金利等の取締りに関する法律第三条、住宅融資保険法第二条第三号、所得税法第百七十四条第八号、船舶油濁等損害賠償保障法第十四条第二項、第四十二条第二項及び第五十条第二項、犯罪による収益の移転防止に関する法律第二条第二項第十七号、予算決算及び会計令第七十七条第一号及び第百条の三第一号及び第二号、中小企業信用保険法施行令第一条の三第十号、漁船損害等補償法施行令第二十四条、公認会計士法施行令第二条第一項第二号、関税法施行令第六十二条の七第一項及び第六十二条の二十一第一項、自動車損害賠償保障法施行令、自動車事故対策事業賦課金等の金額を定める政令第一条、割賦販売法施行令第七条、法人税法施行令第八十四条、金融商品取引法施行令第一条の九第二号（金融商品取引法第二十七条の二十八第三項に係るものに限る。）及び第十五条の十三、印紙税法施行令第二十二条第二号、外航船舶建造融資利子補給臨時措置法施行令第一条第三号、船舶の所有者等の責任の制限に関する法律施行令第六号、ゴルフ場等に係る会員契約の適正化に関する法律施行令第二条、金融機関の信託業務の兼営等に関する法律施行令第五条、金融サービスの提供及び利用環境の整備等に関する法律施行令第二十七条、信託業法施行令第十条、資金決済に関する法律施行令第八条第二項第一号及び第十六条第二項第一号並びに株式会社国際協力銀行法施行令第一条の規定の適用については保険契約者保護機構を保険会社とみなし、損害保険料率算出団体に関する法律第二条第二項、地方税法第三十四条第一項第五号及び第七項並びに第三百十四条の二第一項第五号及び第七項、準備預金制度に関する法律第二条第一項第七号、国民年金法第百二十八条第五項及び第百三十七条の十五第六項、所得税法第七十六条第五項第一号及び第六項第四号、第百六十一条第一項第十四号並びに第二百二十五条第一項第四号、印紙税法別表第三、勤労者財産形成促進法第六条、第六条の二及び第十二条、確定給付企業年金法第九十一条の十八第七項及び第九十三条、相続税法施行令第一条の二第一項第一号、所得税法施行令第三十条第一号、第七十六条第二項第一号、第百八十三条第三項第一号、第二百九条第一項、第二百二十五条の三第一項第三号、第二百二十五条の十、第二百八十条第一項第三号、第二百九十八条第六項第一号及び第三百二十六条第二項第一号、法人税法施行令第百四十五条の三第一項第三号、第百四十五条の九、第百七十七条第一項第三号並びに附則第十六条第一項、第十七条及び第十八条、国家公務員共済組合及び国家公務員共済組合連合会が行う国家公務員等の財産形成事業に関する政令第四条並びに地方公務員共済組合等が行う地方公務員等の財産形成事業に関する政令第四条の規定の適用については生命保険契約者保護機構を生命保険会社とみなし、損害保険料率算出団体に関する法律第二条第一項第四号、第三条第一項及び第二項、第六条、第七条並びに第十条第一項、船主相互保険組合法第八条、地方税法第三十四条第一項第五号及び第七項並びに第三百十四条の二第一項第五号及び第七項、自動車損害賠償保障法、原子力損害の賠償に関する法律第八条、所得税法第九条第一項第十八号、第七十六条第六項第四号、第七十七条第二項第一号、第百六十一条第一項第十四号及び第二百二十五条第一項第五号、地震保険に関する法律、印紙税法別表第三、勤労者財産形成促進法第六条、第六条の二及び第十二条、人工衛星等の打上げ及び人工衛星の管理に関する法律第二条第九号、相続税法施行令第一条の二第二項第一号、貿易保険法施行令第十八条、所得税法施行令第三十条第一号、第百八十四条第二項、第二百二十五条の三第一項第三号、第二百二十五条の十、第二百八十条第一項第三号、第二百九十八条第六項第二号、第三百二十条第二項及び第三百二十六条第二項第一号、法人税法施行令第百四十五条の三第一項第三号、第百四十五条の九及び第百七十七条第一項第三号、地震保険に関する法律施行令第三条、船舶油濁等損害賠償保障法施行令第三条第一項（第三号に係る部分に限る。）、第二項（第一号のうち同条第一項第三号に係る部分に限る。）及び第三項（第一号のうち同条第一項第三号に係る部分に限る。）、国家公務員共済組合及び国家公務員共済組合連合会が行う国家公務員等の財産形成事業に関する政令第四条、地方公務員共済組合等が行う地方公務員等の財産形成事業に関する政令第四条並びに金融サービスの提供及び利用環境の整備等に関する法律施行令第二十九条の規定の適用については損害保険契約者保護機構を損害保険会社とみなす。"
        },
        "referred": {
            "lawNum": "平成十二年政令第四百八十四号",
            "lawArticle": {
                "provision": "MainProvision",
                "article": "27",
                "paragraph": "1",
                "item": "0"
            },
            "text": "金融サービス仲介業者は、法第二十二条第三項の契約を締結する場合には、銀行（銀行法第二条第一項に規定する銀行をいう。第三十条第一項において同じ。）、保険会社（保険業法第二百十九条第一項の免許を受けた同項に規定する特定法人の同項に規定する引受社員を含む。）その他内閣府令で定める金融機関を相手方とし、その内容を次に掲げる要件に適合するものとしなければならない。"
        },
        "match": "令で定める"
    },
    {
        "ref": {
            "lawNum": "平成七年政令第四百二十五号",
            "lawArticle": {
                "provision": "MainProvision",
                "article": "37_4_5",
                "paragraph": "1",
                "item": "0"
            },
            "text": "法第二百七十条の六第三項に規定する政令で定める法令は、臨時金利調整法（昭和二十二年法律第百八十一号）、消防法（昭和二十三年法律第百八十六号）、損害保険料率算出団体に関する法律（昭和二十三年法律第百九十三号）、相続税法（昭和二十五年法律第七十三号）、船主相互保険組合法（昭和二十五年法律第百七十七号）、地方税法（昭和二十五年法律第二百二十六号）、税理士法（昭和二十六年法律第二百三十七号）、漁船損害等補償法（昭和二十七年法律第二十八号）、出資の受入れ、預り金及び金利等の取締りに関する法律（昭和二十九年法律第百九十五号）、住宅融資保険法（昭和三十年法律第六十三号）、自動車損害賠償保障法（昭和三十年法律第九十七号）、準備預金制度に関する法律（昭和三十二年法律第百三十五号）、国民年金法（昭和三十四年法律第百四十一号）、原子力損害の賠償に関する法律、所得税法（昭和四十年法律第三十三号）、地震保険に関する法律（昭和四十一年法律第七十三号）、印紙税法（昭和四十二年法律第二十三号）、勤労者財産形成促進法（昭和四十六年法律第九十二号）、船舶油濁等損害賠償保障法（昭和五十年法律第九十五号）、確定給付企業年金法（平成十三年法律第五十号）、犯罪による収益の移転防止に関する法律、人工衛星等の打上げ及び人工衛星の管理に関する法律、予算決算及び会計令（昭和二十二年勅令第百六十五号）、相続税法施行令（昭和二十五年政令第七十一号）、中小企業信用保険法施行令（昭和二十五年政令第三百五十号）、漁船損害等補償法施行令（昭和二十七年政令第六十八号）、公認会計士法施行令（昭和二十七年政令第三百四十三号）、貿易保険法施行令、関税法施行令（昭和二十九年政令第百五十号）、自動車損害賠償保障法施行令（昭和三十年政令第二百八十六号）、自動車事故対策事業賦課金等の金額を定める政令（昭和三十年政令第三百十六号）、割賦販売法施行令（昭和三十六年政令第三百四十一号）、所得税法施行令（昭和四十年政令第九十六号）、法人税法施行令（昭和四十年政令第九十七号）、金融商品取引法施行令、地震保険に関する法律施行令（昭和四十一年政令第百六十四号）、印紙税法施行令（昭和四十二年政令第百八号）、外航船舶建造融資利子補給臨時措置法施行令（昭和四十四年政令第百九十五号）、船舶油濁等損害賠償保障法施行令、船舶の所有者等の責任の制限に関する法律施行令、国家公務員共済組合及び国家公務員共済組合連合会が行う国家公務員等の財産形成事業に関する政令（昭和五十二年政令第百九十九号）、地方公務員共済組合等が行う地方公務員等の財産形成事業に関する政令（昭和五十三年政令第二十五号）、ゴルフ場等に係る会員契約の適正化に関する法律施行令、金融機関の信託業務の兼営等に関する法律施行令、金融サービスの提供及び利用環境の整備等に関する法律施行令（平成十二年政令第四百八十四号）、信託業法施行令、資金決済に関する法律施行令（平成二十二年政令第十九号）及び株式会社国際協力銀行法施行令（平成二十三年政令第二百二十一号）とし、臨時金利調整法第一条第一項、消防法第三十三条、相続税法第五十九条第一項第一号及び第二項、税理士法第五条第一項第一号ハ、漁船損害等補償法第百十二条第七項、出資の受入れ、預り金及び金利等の取締りに関する法律第三条、住宅融資保険法第二条第三号、所得税法第百七十四条第八号、船舶油濁等損害賠償保障法第十四条第二項、第四十二条第二項及び第五十条第二項、犯罪による収益の移転防止に関する法律第二条第二項第十七号、予算決算及び会計令第七十七条第一号及び第百条の三第一号及び第二号、中小企業信用保険法施行令第一条の三第十号、漁船損害等補償法施行令第二十四条、公認会計士法施行令第二条第一項第二号、関税法施行令第六十二条の七第一項及び第六十二条の二十一第一項、自動車損害賠償保障法施行令、自動車事故対策事業賦課金等の金額を定める政令第一条、割賦販売法施行令第七条、法人税法施行令第八十四条、金融商品取引法施行令第一条の九第二号（金融商品取引法第二十七条の二十八第三項に係るものに限る。）及び第十五条の十三、印紙税法施行令第二十二条第二号、外航船舶建造融資利子補給臨時措置法施行令第一条第三号、船舶の所有者等の責任の制限に関する法律施行令第六号、ゴルフ場等に係る会員契約の適正化に関する法律施行令第二条、金融機関の信託業務の兼営等に関する法律施行令第五条、金融サービスの提供及び利用環境の整備等に関する法律施行令第二十七条、信託業法施行令第十条、資金決済に関する法律施行令第八条第二項第一号及び第十六条第二項第一号並びに株式会社国際協力銀行法施行令第一条の規定の適用については保険契約者保護機構を保険会社とみなし、損害保険料率算出団体に関する法律第二条第二項、地方税法第三十四条第一項第五号及び第七項並びに第三百十四条の二第一項第五号及び第七項、準備預金制度に関する法律第二条第一項第七号、国民年金法第百二十八条第五項及び第百三十七条の十五第六項、所得税法第七十六条第五項第一号及び第六項第四号、第百六十一条第一項第十四号並びに第二百二十五条第一項第四号、印紙税法別表第三、勤労者財産形成促進法第六条、第六条の二及び第十二条、確定給付企業年金法第九十一条の十八第七項及び第九十三条、相続税法施行令第一条の二第一項第一号、所得税法施行令第三十条第一号、第七十六条第二項第一号、第百八十三条第三項第一号、第二百九条第一項、第二百二十五条の三第一項第三号、第二百二十五条の十、第二百八十条第一項第三号、第二百九十八条第六項第一号及び第三百二十六条第二項第一号、法人税法施行令第百四十五条の三第一項第三号、第百四十五条の九、第百七十七条第一項第三号並びに附則第十六条第一項、第十七条及び第十八条、国家公務員共済組合及び国家公務員共済組合連合会が行う国家公務員等の財産形成事業に関する政令第四条並びに地方公務員共済組合等が行う地方公務員等の財産形成事業に関する政令第四条の規定の適用については生命保険契約者保護機構を生命保険会社とみなし、損害保険料率算出団体に関する法律第二条第一項第四号、第三条第一項及び第二項、第六条、第七条並びに第十条第一項、船主相互保険組合法第八条、地方税法第三十四条第一項第五号及び第七項並びに第三百十四条の二第一項第五号及び第七項、自動車損害賠償保障法、原子力損害の賠償に関する法律第八条、所得税法第九条第一項第十八号、第七十六条第六項第四号、第七十七条第二項第一号、第百六十一条第一項第十四号及び第二百二十五条第一項第五号、地震保険に関する法律、印紙税法別表第三、勤労者財産形成促進法第六条、第六条の二及び第十二条、人工衛星等の打上げ及び人工衛星の管理に関する法律第二条第九号、相続税法施行令第一条の二第二項第一号、貿易保険法施行令第十八条、所得税法施行令第三十条第一号、第百八十四条第二項、第二百二十五条の三第一項第三号、第二百二十五条の十、第二百八十条第一項第三号、第二百九十八条第六項第二号、第三百二十条第二項及び第三百二十六条第二項第一号、法人税法施行令第百四十五条の三第一項第三号、第百四十五条の九及び第百七十七条第一項第三号、地震保険に関する法律施行令第三条、船舶油濁等損害賠償保障法施行令第三条第一項（第三号に係る部分に限る。）、第二項（第一号のうち同条第一項第三号に係る部分に限る。）及び第三項（第一号のうち同条第一項第三号に係る部分に限る。）、国家公務員共済組合及び国家公務員共済組合連合会が行う国家公務員等の財産形成事業に関する政令第四条、地方公務員共済組合等が行う地方公務員等の財産形成事業に関する政令第四条並びに金融サービスの提供及び利用環境の整備等に関する法律施行令第二十九条の規定の適用については損害保険契約者保護機構を損害保険会社とみなす。"
        },
        "referred": {
            "lawNum": "平成十二年政令第四百八十四号",
            "lawArticle": {
                "provision": "MainProvision",
                "article": "29",
                "paragraph": "1",
                "item": "0"
            },
            "text": "金融サービス仲介業者は、法第二十三条第一項に規定する金融サービス仲介業者賠償責任保険契約を締結する場合には、保険業法第二条第四項に規定する損害保険会社（同条第九項に規定する外国損害保険会社等及び同法第二百十九条第五項の特定損害保険業免許を受けた者の同条第一項に規定する引受社員を含む。）その他内閣府令で定める者を相手方とし、その内容を次に掲げる要件に適合するものとしなければならない。"
        },
        "match": "令で定める"
    }
]